LICENSE
README.md
my_table_db.py
setup.py
my_table_db.egg-info/PKG-INFO
my_table_db.egg-info/SOURCES.txt
my_table_db.egg-info/dependency_links.txt
my_table_db.egg-info/top_level.txt