Metadata-Version: 2.1
Name: my_table_db
Version: 3.3.3
Summary: A small library for conclusion table db
Author: k0ng999
Author-email: baydar_14@mail.ru
License: MIT
License-File: LICENSE
